proxmox_grapple/__init__.py
proxmox_grapple/_version.py
proxmox_grapple/config.py
proxmox_grapple/vma_extractor.py
proxmox_grapple/vzdump_hook_script.py
proxmox_grapple-2.0.2.dist-info/LICENSE
proxmox_grapple-2.0.2.dist-info/METADATA
proxmox_grapple-2.0.2.dist-info/WHEEL
proxmox_grapple-2.0.2.dist-info/entry_points.txt
proxmox_grapple-2.0.2.dist-info/top_level.txt
proxmox_grapple-2.0.2.dist-info/RECORD
