Metadata-Version: 2.1
Name: proxmox-grapple
Version: 2.0.2
Summary: The grappling hook for Proxmox backups.
Author-email: Jason Lingohr <jason@lucid.net.au>
Project-URL: Homepage, https://github.com/lingfish/proxmox-grapple
Project-URL: Issues, https://github.com/lingfish/proxmox-grapple/issues
Classifier: Programming Language :: Python :: 3
Classifier: License :: OSI Approved :: GNU General Public License v3 or later (GPLv3+)
Classifier: Operating System :: OS Independent
Requires-Python: >=3.9
License-File: LICENSE
Requires-Dist: click
Requires-Dist: daiquiri
Requires-Dist: humanize
Requires-Dist: psutil
Requires-Dist: pyyaml
Requires-Dist: dynaconf
